chalice_plus/__init__.py
chalice_plus/authenticators.py
chalice_plus/cli.py
chalice_plus/exceptions.py
chalice_plus/masking.py
chalice_plus/permissions.py
chalice_plus/urls.py
chalice_plus/views.py
chalice_plus/deploy_utils/__init__.py
chalice_plus/deploy_utils/alembic.py
chalice_plus/deploy_utils/config.py
chalice_plus/deploy_utils/files.py
chalice_plus/deploy_utils/ssm.py
chalice_plus-0.0.1.dist-info/LICENSE
chalice_plus-0.0.1.dist-info/METADATA
chalice_plus-0.0.1.dist-info/WHEEL
chalice_plus-0.0.1.dist-info/entry_points.txt
chalice_plus-0.0.1.dist-info/top_level.txt
chalice_plus-0.0.1.dist-info/RECORD
