Metadata-Version: 2.1
Name: chalice-plus
Version: 0.0.1
Summary: Extension for Chalice, adding support for class-based views, SQLAlchemy and more...
Author-email: Kingston Labs <chalice_plus@kingstonlabs.co.uk>
Project-URL: Homepage, https://github.com/kingstonlabs/chalice-plus
Project-URL: Bug Tracker, https://github.com/kingstonlabs/chalice-plus/issues
Classifier: Programming Language :: Python :: 3
Classifier: License :: OSI Approved :: MIT License
Classifier: Operating System :: OS Independent
Requires-Python: >=3.9
License-File: LICENSE
Requires-Dist: boto3
Requires-Dist: chalice
Requires-Dist: marshmallow-sqlalchemy
Requires-Dist: alembic
Requires-Dist: click
